aga8/__init__.py
aga8/detail.py
aga8/tests.py
aga8_python-0.0.1.dist-info/LICENSE
aga8_python-0.0.1.dist-info/METADATA
aga8_python-0.0.1.dist-info/WHEEL
aga8_python-0.0.1.dist-info/top_level.txt
aga8_python-0.0.1.dist-info/RECORD
