Metadata-Version: 2.1
Name: aga8-python
Version: 0.0.1
Summary: Python version of AGA8 detail module.
Home-page: https://github.com/elcolie/AGA8-python
Author: Sarit Ritwirune
Author-email: sarit@elcolie.com
Project-URL: Bug Tracker, https://github.com/elcolie/AGA8-python/issues
License-File: LICENSE
